ppcie/__init__.py
ppcie/verifier/__init__.py
ppcie/verifier/src/__init__.py
ppcie/verifier/src/exceptions/__init__.py
ppcie/verifier/src/exceptions/exception.py
ppcie/verifier/src/gpu_spdm/__init__.py
ppcie/verifier/src/gpu_spdm/spdm_msrt_req_msg.py
ppcie/verifier/src/gpu_spdm/spdm_msrt_resp_msg.py
ppcie/verifier/src/nscq/__init__.py
ppcie/verifier/src/nscq/paths.py
ppcie/verifier/src/nscq/pynscq.py
ppcie/verifier/src/nvml/__init__.py
ppcie/verifier/src/nvml/exceptions.py
ppcie/verifier/src/nvml/nvml_client.py
ppcie/verifier/src/switch_spdm/__init__.py
ppcie/verifier/src/switch_spdm/spdm_msrt_req_msg.py
ppcie/verifier/src/switch_spdm/spdm_msrt_resp_msg.py
ppcie/verifier/src/topology/__init__.py
ppcie/verifier/src/topology/exceptions.py
ppcie/verifier/src/topology/validate_topology.py
ppcie/verifier/src/utils/__init__.py
ppcie/verifier/src/utils/config.py
ppcie/verifier/src/utils/logging.py
ppcie/verifier/src/utils/status.py
ppcie/verifier/verification.py
nv_ppcie_verifier-2.0.0.dist-info/METADATA
nv_ppcie_verifier-2.0.0.dist-info/WHEEL
nv_ppcie_verifier-2.0.0.dist-info/licenses/LICENSE
nv_ppcie_verifier-2.0.0.dist-info/RECORD
