Metadata-Version: 2.4
Name: nv-ppcie-verifier
Version: 2.0.0
Summary: Protected PCIE Verifier SDK CPP
License: OSI Approved :: Apache Software License
License-File: LICENSE
Author: Kartheeka Bokka
Author-email: kartheekab@nvidia.com
Requires-Python: >=3.9,<4.0
Classifier: License :: Other/Proprietary License
Classifier: Programming Language :: Python :: 3
Classifier: Programming Language :: Python :: 3.9
Classifier: Programming Language :: Python :: 3.10
Classifier: Programming Language :: Python :: 3.11
Classifier: Programming Language :: Python :: 3.12
Classifier: Programming Language :: Python :: 3.13
Classifier: Programming Language :: Python :: 3.14
Requires-Dist: astroid (==3.1.0)
Requires-Dist: black (==24.3.0)
Requires-Dist: build (==1.2.1)
Requires-Dist: click (==8.1.7)
Requires-Dist: cryptography (==43.0.1)
Requires-Dist: dill (==0.3.8)
Requires-Dist: ecdsa (==0.18.0)
Requires-Dist: nvidia-ml-py (>=12.550.52,<13.0.0)
Requires-Dist: pathspec (==0.12.1)
Requires-Dist: prettytable (>=3.10.0,<4.0.0)
Requires-Dist: pylint (==3.1.0)
Requires-Dist: pytest (==8.1.1)
Requires-Dist: pytest-cov (>=5.0.0,<6.0.0)
Requires-Dist: setuptools (==80.9.0)
Requires-Dist: timeout-decorator (==0.5.0)
Requires-Dist: tomlkit (==0.12.4)
Requires-Dist: twine (>=3.7.1)
Requires-Dist: typing_extensions (==4.10.0)
Requires-Dist: wheel (==0.43.0)
